pymagnets/__init__.py
pymagnets/_version.py
pymagnets/magnet.py
pymagnets/material.py
pymagnets/model.py
pymagnets-1.2.2.dist-info/LICENSE.txt
pymagnets-1.2.2.dist-info/METADATA
pymagnets-1.2.2.dist-info/WHEEL
pymagnets-1.2.2.dist-info/top_level.txt
pymagnets-1.2.2.dist-info/RECORD
